jupyter_environment_manager/__init__.py
jupyter_environment_manager/_version.py
jupyter_environment_manager/config_logger.py
jupyter_environment_manager/configure.py
jupyter_environment_manager/devices.py
jupyter_environment_manager/envs_create.py
jupyter_environment_manager/envs_list.py
jupyter_environment_manager/envs_pkgs.py
jupyter_environment_manager/envs_remove.py
jupyter_environment_manager/envs_state.py
jupyter_environment_manager/executables.py
jupyter_environment_manager/handlers.py
jupyter_environment_manager/jobs.py
jupyter_environment_manager/kernels.py
jupyter_environment_manager/symlink.py
jupyter_environment_manager-0.3.0.data/data/etc/jupyter/jupyter_server_config.d/jupyter_environment_manager.json
jupyter_environment_manager-0.3.0.data/data/share/jupyter/labextensions/@qbraid/jupyter-environment-manager/package.json
jupyter_environment_manager-0.3.0.data/data/share/jupyter/labextensions/@qbraid/jupyter-environment-manager/static/108.292ff6a96dcaec1dd522.js
jupyter_environment_manager-0.3.0.data/data/share/jupyter/labextensions/@qbraid/jupyter-environment-manager/static/130.004f56f1016843a5db7f.js
jupyter_environment_manager-0.3.0.data/data/share/jupyter/labextensions/@qbraid/jupyter-environment-manager/static/222.9b5d86e6458f74d81b11.js
jupyter_environment_manager-0.3.0.data/data/share/jupyter/labextensions/@qbraid/jupyter-environment-manager/static/239.31b11e3a9a84a9ce2657.js
jupyter_environment_manager-0.3.0.data/data/share/jupyter/labextensions/@qbraid/jupyter-environment-manager/static/239.31b11e3a9a84a9ce2657.js.LICENSE.txt
jupyter_environment_manager-0.3.0.data/data/share/jupyter/labextensions/@qbraid/jupyter-environment-manager/static/247.b47ee76a631bbf654edf.js
jupyter_environment_manager-0.3.0.data/data/share/jupyter/labextensions/@qbraid/jupyter-environment-manager/static/247.b47ee76a631bbf654edf.js.LICENSE.txt
jupyter_environment_manager-0.3.0.dist-info/METADATA
jupyter_environment_manager-0.3.0.dist-info/WHEEL
jupyter_environment_manager-0.3.0.dist-info/licenses/LICENSE
jupyter_environment_manager-0.3.0.dist-info/RECORD
