Metadata-Version: 2.3
Name: jupyter_environment_manager
Version: 0.3.0
Dynamic: Keywords
Summary: JupyterLab extension for managing execution environments, packages, and kernels.
Project-URL: Homepage, https://docs.qbraid.com/lab/user-guide/environments
Project-URL: Bug Tracker, https://github.com/qBraid/community/issues
Project-URL: Repository, https://github.com/qBraid/lab-environment-manager.git
Author-email: qBraid Development Team <contact@qbraid.com>
License: Proprietary
License-File: LICENSE
Classifier: Framework :: Jupyter
Classifier: Framework :: Jupyter :: JupyterLab
Classifier: Framework :: Jupyter :: JupyterLab :: 4
Classifier: Framework :: Jupyter :: JupyterLab :: Extensions
Classifier: Framework :: Jupyter :: JupyterLab :: Extensions :: Prebuilt
Classifier: Programming Language :: Python
Classifier: Programming Language :: Python :: 3
Classifier: Programming Language :: Python :: 3.9
Classifier: Programming Language :: Python :: 3.10
Classifier: Programming Language :: Python :: 3.11
Classifier: Programming Language :: Python :: 3.12
Requires-Python: >=3.9
Requires-Dist: jupyter-server<3,>=2.0.1
Requires-Dist: qbraid-core[environments]>=0.1.18
Requires-Dist: tornado>=6.1.0
Provides-Extra: test
Requires-Dist: pytest-asyncio>=0.23.7; extra == 'test'
Requires-Dist: pytest-cov>=5.0.0; extra == 'test'
Requires-Dist: pytest-jupyter[server]>=0.10.0; extra == 'test'
Requires-Dist: pytest>=8.2.1; extra == 'test'
